exapi/__init__.py
exapi/__main__.py
exapi/client.py
exapi/constants.py
exapi/exceptions.py
exapi/hooks.py
exapi/subject.py
exapi/types.py
exapi/utils.py
exapi/ws.py
exapi/bitget/__init__.py
exapi/bitget/exceptions.py
exapi/bitget/utils.py
exapi/bitget/v1/__init__.py
exapi/bitget/v1/auth.py
exapi/bitget/v1/client.py
exapi/bitget/v1/constants.py
exapi/bitget/v1/enums.py
exapi/bitget/v1/models.py
exapi/bitget/v1/ws.py
exapi/bitget/v1/broker/__init__.py
exapi/bitget/v1/broker/enums.py
exapi/bitget/v1/mix/__init__.py
exapi/bitget/v1/mix/enums.py
exapi/bitget/v1/mix/ws.py
exapi/bitget/v1/spot/__init__.py
exapi/bitget/v1/spot/enums.py
exapi/bitget/v1/spot/ws.py
exapi/bitget/v1/spot/client/__init__.py
exapi/bitget/v1/spot/client/client.py
exapi/bitget/v1/spot/client/account/__init__.py
exapi/bitget/v1/spot/client/account/account.py
exapi/bitget/v1/spot/client/account/models.py
exapi/bitget/v1/spot/client/market/__init__.py
exapi/bitget/v1/spot/client/market/market.py
exapi/bitget/v1/spot/client/market/models.py
exapi/bitget/v1/spot/client/public/__init__.py
exapi/bitget/v1/spot/client/public/models.py
exapi/bitget/v1/spot/client/public/public.py
exapi/bitget/v1/spot/client/trade/__init__.py
exapi/bitget/v1/spot/client/trade/models.py
exapi/bitget/v1/spot/client/trade/trade.py
exapi/bitget/v1/spot/client/wallet/__init__.py
exapi/bitget/v1/spot/client/wallet/models.py
exapi/bitget/v1/spot/client/wallet/wallet.py
exapi/bybit/__init__.py
exapi/bybit/exceptions.py
exapi/bybit/utils.py
exapi/bybit/v3/__init__.py
exapi/bybit/v3/auth.py
exapi/bybit/v3/client.py
exapi/bybit/v3/constants.py
exapi/bybit/v3/enums.py
exapi/bybit/v3/models.py
exapi/bybit/v3/ws.py
exapi/bybit/v3/asset/__init__.py
exapi/bybit/v3/asset/client.py
exapi/bybit/v3/asset/enums.py
exapi/bybit/v3/asset/models.py
exapi/bybit/v3/spot/__init__.py
exapi/bybit/v3/spot/enums.py
exapi/bybit/v3/spot/client/__init__.py
exapi/bybit/v3/spot/client/client.py
exapi/bybit/v3/spot/client/private/__init__.py
exapi-0.1.1.dist-info/METADATA
exapi-0.1.1.dist-info/WHEEL
exapi-0.1.1.dist-info/licenses/LICENSE.txt
exapi-0.1.1.dist-info/RECORD
