Metadata-Version: 2.1
Name: exapi
Version: 0.1.1
Summary: Async API for exchanges
Project-URL: GitHub, https://github.com/miviskin/exapi
Author-email: miviskin <miviskin@gmail.com>
License-File: LICENSE.txt
Classifier: License :: OSI Approved :: MIT License
Classifier: Operating System :: OS Independent
Classifier: Programming Language :: Python :: 3.11
Requires-Python: >=3.11
Requires-Dist: anyio~=3.6.2
Requires-Dist: httpx~=0.23.1
Requires-Dist: pydantic~=1.10
Requires-Dist: python-dotenv~=0.21.0
Requires-Dist: uvloop~=0.16
Requires-Dist: websockets~=10.4
Provides-Extra: dev
Requires-Dist: build; extra == 'dev'
Requires-Dist: hatch; extra == 'dev'
Requires-Dist: pytest; extra == 'dev'
Requires-Dist: pytest-asyncio; extra == 'dev'
Requires-Dist: pytest-cov; extra == 'dev'
Requires-Dist: pytest-httpx; extra == 'dev'
Requires-Dist: python-dotenv; extra == 'dev'
Requires-Dist: twine; extra == 'dev'
